__init__.py
backbone.py
callbacks.py
callbacks_wandb.py
datamodule.py
factory.py
model.py
module.py
mrl.py
utils.py
claymodel-1.5.0.dist-info/licenses/LICENSE
claymodel-1.5.0.dist-info/METADATA
claymodel-1.5.0.dist-info/WHEEL
claymodel-1.5.0.dist-info/top_level.txt
claymodel-1.5.0.dist-info/RECORD
