Metadata-Version: 2.4
Name: claymodel
Version: 1.5.0
Summary: https://clay-foundation.github.io/model/
Requires-Python: >=3.11
License-File: LICENSE
Requires-Dist: torch==2.4.0
Requires-Dist: torchvision==0.19.0
Requires-Dist: einops~=0.7.0
Requires-Dist: geopandas
Requires-Dist: jsonargparse[signatures]>=4.27.7
Requires-Dist: lightning
Requires-Dist: matplotlib
Requires-Dist: python-box
Requires-Dist: scikit-image
Requires-Dist: scikit-learn
Requires-Dist: timm
Requires-Dist: vit-pytorch
Requires-Dist: wandb
Dynamic: license-file
